HISTORY.txt
MANIFEST.in
README.txt
TODO.txt
setup.cfg
setup.py
docs/HISTORY.txt
docs/INSTALL.txt
docs/LICENSE.txt
garbas/__init__.py
garbas.forum.egg-info/PKG-INFO
garbas.forum.egg-info/SOURCES.txt
garbas.forum.egg-info/dependency_links.txt
garbas.forum.egg-info/entry_points.txt
garbas.forum.egg-info/namespace_packages.txt
garbas.forum.egg-info/not-zip-safe
garbas.forum.egg-info/requires.txt
garbas.forum.egg-info/top_level.txt
garbas/forum/__init__.py
garbas/forum/browser.txt
garbas/forum/config.py
garbas/forum/configure.zcml
garbas/forum/content.txt
garbas/forum/interfaces.py
garbas/forum/notification.py
garbas/forum/notification.txt
garbas/forum/permissions.py
garbas/forum/permissions.zcml
garbas/forum/tests.py
garbas/forum/browser/__init__.py
garbas/forum/browser/configure.zcml
garbas/forum/browser/content_view.pt
garbas/forum/browser/forum.py
garbas/forum/browser/post.py
garbas/forum/browser/topic.py
garbas/forum/browser/css/main.css
garbas/forum/browser/icons/forum_icon.gif
garbas/forum/browser/icons/post_icon.gif
garbas/forum/browser/icons/topic_icon.gif
garbas/forum/browser/images/last_post.gif
garbas/forum/browser/images/read_forum.gif
garbas/forum/browser/images/read_post.gif
garbas/forum/browser/images/unread_post.gif
garbas/forum/browser/kss/forum.kss
garbas/forum/browser/templates/add_post.pt
garbas/forum/browser/templates/add_topic.pt
garbas/forum/browser/templates/forum.pt
garbas/forum/browser/templates/topic.pt
garbas/forum/content/__init__.py
garbas/forum/content/base.py
garbas/forum/content/configure.zcml
garbas/forum/content/forum.py
garbas/forum/content/forum.txt
garbas/forum/content/post.py
garbas/forum/content/topic.py
garbas/forum/locales/README
garbas/forum/locales/garbas.forum-generated.pot
garbas/forum/locales/garbas.forum-manual.pot
garbas/forum/locales/garbas.forum.pot
garbas/forum/locales/sl/LC_MESSAGES/garbas.forum.mo
garbas/forum/locales/sl/LC_MESSAGES/garbas.forum.po
garbas/forum/profiles/default/catalog.xml
garbas/forum/profiles/default/cssregistry.xml
garbas/forum/profiles/default/factorytool.xml
garbas/forum/profiles/default/kssregistry.xml
garbas/forum/profiles/default/propertiestool.xml
garbas/forum/profiles/default/rolemap.xml
garbas/forum/profiles/default/skins.xml
garbas/forum/profiles/default/types.xml
