Metadata-Version: 1.0
Name: garbas.forum
Version: 0.1b9
Summary: Forum for Plone
Home-page: http://github.com/garbas/garbas.forum/tree/master
Author: Rok Garbas
Author-email: rok.garbas@gmail.com
License: GPL
Platform: UNKNOWN
Classifier: Framework :: Plone
Classifier: Framework :: Zope2
Classifier: Framework :: Zope3
Classifier: Programming Language :: Python
Classifier: Topic :: Software Development :: Libraries :: Python Modules
